trab3/RAM16k/RAM16k.v
module RAM16k(
    input  [15:0] in,
    input  [13:0]  address,
    input         load,
    input         clk,
    output reg [15:0] out 
);
    reg [15:0] ram [2**13:0]; // Define 8 registradores de 16 bits cada

    always @ (*) begin
        if (load) begin
            ram[address] <= in; 
        end

        out = ram[address]; 
    end
    
endmodule

trab3/RAM16k/tb_RAM16k.v
`include "RAM16k.v"

module tb_RAM16k;

    reg [15:0]  in;
    reg [13:0]   address;
    reg load; 
    reg clk;
    wire [15:0] out;

    RAM16k uut(in, address, load, clk, out);


    initial begin
        $display("Testando o módulo RAM16k");
        $dumpfile("signals.vcd");
        $dumpvars(0, tb_RAM16k);
        // load in data
        clk = 0;
        load = 1;
        in = 0;

        in = 16'b0000000000000000; address = 3'b000; // address 0
        #2 in = 16'b1111111111111111; address = 3'b001; // address 1
        #2 in = 16'b0000000011111111; address = 3'b010;load = 0; // address 2
        #2 in = 16'b1111111100000000; address = 3'b011;load = 1; // address 3
        #2 in = 16'b0000111100001111; address = 3'b100; // address 4
        #2 in = 16'b1111000011110000; address = 3'b101; // address 5
        #2 in = 16'b0011001100110011; address = 3'b110; // address 6
        #2 in = 16'b1100110011001100; address = 3'b111; // address 7

        #2 in = 16'b0000000000000000; address = 6'b010100; // address 20
        #2 in = 16'b1111111111111111; address = 6'b111111; // address 63
        #2 in = 16'b0000010011100111; address = 3'b010;load = 0; // address 2
        #2 in = 16'b1111100100000000; address = 3'b011;load = 1; // address 3
        #2 in = 16'b0000111100001001; address = 6'b011100; // address 28
        #2 in = 16'b1111011011110000; address = 6'b100000; // address 32
        #2 in = 16'b0011001100111011; address = 6'b101001; // address 41
        #2 in = 16'b1100110011001101; address = 6'b111000; // address 56
        #2 $finish;
    end
        // Monitora os sinais
    initial begin
        $monitor("Tempo = %0t | clk = %b | address = %b | out = %b", $time, clk, address, out);
    end

    always 
        #2 clk = ~clk;
        

endmodule

trab3/RAM16k/signals.vcd
$date
	Sat Aug 24 17:41:20 2024
$end
$version
	Icarus Verilog
$end
$timescale
	1s
$end
$scope module tb_RAM16k $end
$var wire 16 ! out [15:0] $end
$var reg 14 " address [13:0] $end
$var reg 1 # clk $end
$var reg 16 $ in [15:0] $end
$var reg 1 % load $end
$scope module uut $end
$var wire 14 & address [13:0] $end
$var wire 1 # clk $end
$var wire 16 ' in [15:0] $end
$var wire 1 % load $end
$var reg 16 ( out [15:0] $end
$upscope $end
$upscope $end
$enddefinitions $end
$comment Show the parameter values. $end
$dumpall
$end
#0
$dumpvars
b0 (
b0 '
b0 &
1%
b0 $
0#
b0 "
b0 !
$end
#2
b1111111111111111 !
b1111111111111111 (
1#
b1 "
b1 &
b1111111111111111 $
b1111111111111111 '
#4
bx !
bx (
0#
0%
b10 "
b10 &
b11111111 $
b11111111 '
#6
b1111111100000000 !
b1111111100000000 (
1#
1%
b11 "
b11 &
b1111111100000000 $
b1111111100000000 '
#8
b111100001111 !
b111100001111 (
0#
b100 "
b100 &
b111100001111 $
b111100001111 '
#10
b1111000011110000 !
b1111000011110000 (
1#
b101 "
b101 &
b1111000011110000 $
b1111000011110000 '
#12
b11001100110011 !
b11001100110011 (
0#
b110 "
b110 &
b11001100110011 $
b11001100110011 '
#14
b1100110011001100 !
b1100110011001100 (
1#
b111 "
b111 &
b1100110011001100 $
b1100110011001100 '
#16
b0 !
b0 (
0#
b10100 "
b10100 &
b0 $
b0 '
#18
b1111111111111111 !
b1111111111111111 (
1#
b111111 "
b111111 &
b1111111111111111 $
b1111111111111111 '
#20
bx !
bx (
0#
0%
b10 "
b10 &
b10011100111 $
b10011100111 '
#22
b1111100100000000 !
b1111100100000000 (
1#
1%
b11 "
b11 &
b1111100100000000 $
b1111100100000000 '
#24
b111100001001 !
b111100001001 (
0#
b11100 "
b11100 &
b111100001001 $
b111100001001 '
#26
b1111011011110000 !
b1111011011110000 (
1#
b100000 "
b100000 &
b1111011011110000 $
b1111011011110000 '
#28
b11001100111011 !
b11001100111011 (
0#
b101001 "
b101001 &
b11001100111011 $
b11001100111011 '
#30
b1100110011001101 !
b1100110011001101 (
1#
b111000 "
b111000 &
b1100110011001101 $
b1100110011001101 '
