trab3/DFF_sem_rst/DFF_sem_rst.v
// Sflip flop tipo D sem rst

module DFF_sem_rst(input d, input clk, output reg q, output reg qn);
  
  always @ ( posedge clk) begin
    
      q <= d;
      qn <= ~d;
    
  end

endmodule

trab3/Bit/mux.v
//
// Multiplexador de duas entradas (1 bit), comportamental
//
module mux(
  input a, input b,
  input sel,
  output y);
  
  assign y = sel? b : a;

endmodule

trab3/Bit/Bit.v
`include "DFF_sem_rst.v"
`include "mux.v"

module Bit(input in1, input load, input clk, output reg out);

    wire q;
    wire qn;
    wire mux_out;

    // Instanciando o mux
    mux aux_mux(q, in1, load, mux_out);

    // Instanciando o flip-flop
    DFF_sem_rst dff(mux_out, clk, q, qn); 

    // Atualizando o valor de out
    always @ (posedge clk) begin
        out <= q;
    end

endmodule

trab3/Bit/tb_Bit.v
// módulos usados
`include "Bit.v"

module tb_Bit;
  
  // clock simulado
  reg clk;

  // sinais
  reg in1;
  reg load;
  wire out;
  
  // Instância da UUT (Unit Under Test)
  Bit uut (
    in1, 
    load, 
    clk, 
    out
  );

  // Como os sinais irão variar durante a simulação
  initial begin
    $display("Testando o módulo Bit");
    $dumpfile("signals.vcd");
    $dumpvars(0, tb_Bit);
    
    // Inicialização dos sinais
    clk = 0;
    in1 = 0;
    load = 0;

    // Sequência de teste
    #2 in1 = 1; load = 1; // Carrega '1' no registrador
    #2 load = 0;          // Desativa o carregamento
    #2 in1 = 0;           // Muda o valor de in1, mas sem carregar
    #2 load = 1;          // Carrega '0' no registrador
    #2 load = 0;
    #2 in1 = 1; load = 1; // Carrega '1' novamente
    #2 load = 0;

    #5 $finish;
  end

  // Monitora os sinais
  initial begin
    $monitor("Tempo = %0t | clk = %b | load = %b | in1 = %b | out = %b", $time, clk, load, in1, out);
  end

  // Gerador de clock com bloco always de única linha
  always 
    #1 clk = ~clk;

endmodule

trab3/Bit/signals.vcd
$date
	Sat Aug 24 12:33:59 2024
$end
$version
	Icarus Verilog
$end
$timescale
	1s
$end
$scope module tb_Bit $end
$var wire 1 ! out $end
$var reg 1 " clk $end
$var reg 1 # in1 $end
$var reg 1 $ load $end
$scope module uut $end
$var wire 1 " clk $end
$var wire 1 # in1 $end
$var wire 1 $ load $end
$var wire 1 % qn $end
$var wire 1 & q $end
$var wire 1 ' mux_out $end
$var reg 1 ! out $end
$scope module aux_mux $end
$var wire 1 # b $end
$var wire 1 $ sel $end
$var wire 1 ' y $end
$var wire 1 & a $end
$upscope $end
$scope module dff $end
$var wire 1 " clk $end
$var wire 1 ' d $end
$var reg 1 & q $end
$var reg 1 % qn $end
$upscope $end
$upscope $end
$upscope $end
$enddefinitions $end
$comment Show the parameter values. $end
$dumpall
$end
#0
$dumpvars
x'
x&
x%
0$
0#
0"
x!
$end
#1
1"
#2
1'
0"
1$
1#
#3
0%
1&
1"
#4
0"
0$
#5
1!
1"
#6
0"
0#
#7
1"
#8
0'
0"
1$
#9
1%
0&
1"
#10
0"
0$
#11
0!
1"
#12
1'
0"
1$
1#
#13
0%
1&
1"
#14
0"
0$
#15
1!
1"
