trab2/inc16/inc16.v
//
// Incremento de uma unidade de um número de 16bits
//

module inc16 (
    input [15:0] in,
    output [15:0] out
);

    assign out = in + 1;

endmodule

trab2/alu/alu.v
`include "inc16.v"
module alu(
    //Entradas
    input [15:0] x, 
    input [15:0] y,     
    input zx, 
    input nx, 
    input zy, 
    input ny, 
    input f, 
    input no,
    //Saidas
    output reg [15:0] out,      
    output zr, 
    output ng    
    );

    wire [5:0] sel;
    assign sel[5] = zx;
    assign sel[4] = nx;
    assign sel[3] = zy;
    assign sel[2] = ny;
    assign sel[1] = f;
    assign sel[0] = no;

    always @(*) begin
        case (sel)
            6'b101010: out = 0;
            6'b111111: out = 1;
            6'b111010: out = -1;
            6'b001100: out = x;
            6'b110000: out = y;
            6'b001101: out = ~x;
            6'b110001: out = ~y;
            6'b001111: out = -x;
            6'b110011: out = -y;
            6'b011111: out = x+1;
            6'b110111: out = y+1;
            6'b000010: out = x + y;
            6'b010011: out = x - y;
            6'b000111: out = y - x;
            6'b000000: out = x & y;
            6'b010101: out = x | y;
        endcase
    end

    assign zr = (out == 0) ? 1 : 0;
    assign ng = out[15];

endmodule

trab2/alu/alu_tb.v
`include "alu.v"

module alu_tb;

    reg [15:0] in_x; 
    reg [15:0] in_y;     
    reg in_zx; 
    reg in_nx; 
    reg in_zy; 
    reg in_ny; 
    reg in_f; 
    reg in_no;
    wire [15:0] out_out;      
    wire out_zr; 
    wire out_ng; 
    
    alu uut (
        .x(in_x), 
        .y(in_y), 
        .zx(in_zx), 
        .nx(in_nx), 
        .zy(in_zy), 
        .ny(in_ny),
        .f(in_f), 
        .no(in_no), 
        .out(out_out), 
        .zr(out_zr), 
        .ng(out_ng)
    );

    initial begin
        $display("Testbench para o ALU");
        $dumpfile("signals.vcd");
        $dumpvars(0,alu_tb);

        # 0 in_x = 16'h0000; in_y = 16'h0000; in_zx = 1; in_nx = 0; in_zy = 1; in_ny = 0; in_f = 1; in_no = 0;
        # 10 in_x = 16'hFFFF; in_y = 16'h0000; in_zx = 1; in_nx = 1; in_zy = 1; in_ny = 1; in_f = 1; in_no = 1;
        # 10 in_x = $random; in_y = $random; in_zx = 1; in_nx = 1; in_zy = 1; in_ny = 0; in_f = 1; in_no = 0;
        # 10 in_x = $random; in_y = $random; in_zx = 0; in_nx = 0; in_zy = 1; in_ny = 1; in_f = 0; in_no = 0;
        # 10 in_x = $random; in_y = $random; in_zx = 1; in_nx = 1; in_zy = 0; in_ny = 0; in_f = 0; in_no = 0;
        # 10 in_x = $random; in_y = $random; in_zx = 0; in_nx = 0; in_zy = 1; in_ny = 1; in_f = 0; in_no = 1;
        # 10 in_x = $random; in_y = $random; in_zx = 1; in_nx = 1; in_zy = 0; in_ny = 0; in_f = 0; in_no = 1;
        # 10 in_x = $random; in_y = $random; in_zx = 0; in_nx = 0; in_zy = 1; in_ny = 1; in_f = 1; in_no = 1;
        # 10 in_x = $random; in_y = $random; in_zx = 1; in_nx = 1; in_zy = 0; in_ny = 0; in_f = 1; in_no = 1;
        # 10 in_x = 16'hFFFF; in_y = 16'hFFFF; in_zx = 0; in_nx = 1; in_zy = 1; in_ny = 1; in_f = 1; in_no = 1;


        # 10 $finish;
    end

    // Monitora os sinais
    initial begin
        $monitor("t=%03d: \tx=%d,y=%d,zx=%d,nx=%d,zy=%d,ny=%d,f=%d,no=%d,s=%d,o=%d,zr=%d,ng=%d \n",$time,
                 in_x,in_y,in_zx,in_nx,in_zy,in_ny,in_f,in_no,out_out,out_zr,out_ng);
    end

endmodule

trab2/alu/signals.vcd
$date
	Wed Aug 21 15:28:46 2024
$end
$version
	Icarus Verilog
$end
$timescale
	1s
$end
$scope module alu_tb $end
$var wire 1 ! out_zr $end
$var wire 16 " out_out [15:0] $end
$var wire 1 # out_ng $end
$var reg 1 $ in_f $end
$var reg 1 % in_no $end
$var reg 1 & in_nx $end
$var reg 1 ' in_ny $end
$var reg 16 ( in_x [15:0] $end
$var reg 16 ) in_y [15:0] $end
$var reg 1 * in_zx $end
$var reg 1 + in_zy $end
$scope module uut $end
$var wire 1 $ f $end
$var wire 1 % no $end
$var wire 1 & nx $end
$var wire 1 ' ny $end
$var wire 16 , x [15:0] $end
$var wire 16 - y [15:0] $end
$var wire 1 * zx $end
$var wire 1 + zy $end
$var wire 1 ! zr $end
$var wire 6 . sel [5:0] $end
$var wire 1 # ng $end
$var reg 16 / out [15:0] $end
$upscope $end
$upscope $end
$enddefinitions $end
$comment Show the parameter values. $end
$dumpall
$end
#0
$dumpvars
b0 /
b101010 .
b0 -
b0 ,
1+
1*
b0 )
b0 (
0'
0&
0%
1$
0#
b0 "
1!
$end
#10
0!
b1 "
b1 /
1%
1'
b111111 .
1&
b1111111111111111 (
b1111111111111111 ,
#20
1#
b1111111111111111 "
b1111111111111111 /
0%
b111010 .
0'
b101111010000001 )
b101111010000001 -
b11010100100100 (
b11010100100100 ,
#30
b1101011000001001 "
b1101011000001001 /
0$
1'
0&
b1100 .
0*
b101011001100011 )
b101011001100011 -
b1101011000001001 (
b1101011000001001 ,
#40
b1001100110001101 "
b1001100110001101 /
0'
0+
1&
b110000 .
1*
b1001100110001101 )
b1001100110001101 -
b111101100001101 (
b111101100001101 ,
#50
0#
b111101110011010 "
b111101110011010 /
1%
1'
1+
0&
b1101 .
0*
b101001000010010 )
b101001000010010 -
b1000010001100101 (
b1000010001100101 ,
#60
b11001011110010 "
b11001011110010 /
0'
0+
1&
b110001 .
1*
b1100110100001101 )
b1100110100001101 -
b1110001100000001 (
b1110001100000001 ,
#70
b111010001010 "
b111010001010 /
1$
1'
1+
0&
b1111 .
0*
b1100110100111101 )
b1100110100111101 -
b1111000101110110 (
b1111000101110110 ,
#80
b100001110100 "
b100001110100 /
0'
0+
1&
b110011 .
1*
b1111011110001100 )
b1111011110001100 -
b101011111101101 (
b101011111101101 ,
#90
1!
b0 "
b0 /
1'
1+
b11111 .
0*
b1111111111111111 )
b1111111111111111 -
b1111111111111111 (
b1111111111111111 ,
