trab5/cpu/alu.v
module alu(
    //Entradas
    input [15:0] x, 
    input [15:0] y,     
    input zx, 
    input nx, 
    input zy, 
    input ny, 
    input f, 
    input no,
    //Saidas
    output reg [15:0] out,      
    output zr, 
    output ng    
    );

    wire [5:0] sel;
    assign sel[5] = zx;
    assign sel[4] = nx;
    assign sel[3] = zy;
    assign sel[2] = ny;
    assign sel[1] = f;
    assign sel[0] = no;

    always @(*) begin
        case (sel)
            6'b101010: out = 0;
            6'b111111: out = 1;
            6'b111010: out = -1;
            6'b001100: out = x;
            6'b110000: out = y;
            6'b001101: out = ~x;
            6'b110001: out = ~y;
            6'b001111: out = -x;
            6'b110011: out = -y;
            6'b011111: out = x+1;
            6'b110111: out = y+1;
            6'b000010: out = x + y;
            6'b010011: out = x - y;
            6'b000111: out = y - x;
            6'b000000: out = x & y;
            6'b010101: out = x | y;
        endcase
    end

    assign zr = (out == 0) ? 1 : 0;
    assign ng = out[15];

endmodule

trab5/cpu/CPU.v
`include "alu.v"
module CPU(
    input wire clk,
    input wire [15:0] inM,          // M value input  (M = contents of RAM[A])
    input wire [15:0] instruction,  // Instruction for execution
    input wire reset,               // Signals whether to re-start the current
                                    // program (rstn==1) or continue executing
                                    // the current program (rstn==0).

    output wire [15:0] outM,        // M value output
    output wire loadM,              // Write to M? 
    output wire [15:0] addressM,    // Address in data memory (of M) to read
    output reg [15:0] pc            // address of next instruction
);

    // your implementation comes here:

    assign addressM = regA;
    wire loadI;
    wire loadA;
    wire loadD;
    assign outM = outALU;    
    wire [15:0] am;
    assign am = (instruction[12]) ? inM : regA;
    wire lt;
    wire eq;
    wire jmp;
    wire inc;
    wire [15:0] outALU;
        
    reg [15:0] regA;
    reg [15:0] regD;

    alu alu_0(
        .x(regD),
        .y(am),
        .zx(instruction[11]),
        .nx(instruction[10]),
        .zy(instruction[9]),
        .ny(instruction[8]),
        .f(instruction[7]),
        .no(instruction[6]),
        .out(outALU),
        .zr(eq),
        .ng(lt)
    );
    assign loadI = ~instruction[15];
    assign loadA = instruction[15] & instruction[5];
    assign loadD = instruction[15] & instruction[4];
    assign loadM = instruction[15] & instruction[3];
    assign jmp = instruction[15] & ((lt & instruction[2]) | (eq & instruction[1]) | ((!(lt|eq)) & instruction[0]));
    
    always @(posedge clk)
        if (reset) pc <= 0;
        else if (jmp) pc <= regA;
        else pc <= pc+1;

    always @(posedge clk)
        if (reset) regA <= 0;
        else if (loadI) regA <= instruction;
        else if (loadA) regA <= outALU;
        else regA <= regA;
    
    always @(posedge clk)
        if (reset) regD <= 0;
        else if (loadD) regD <= outALU;
        else regD <= regD;
    
endmodule

trab5/cpu/tb_CPU.v
// módulos usados
`include "CPU.v"

module tb_CPU;
    // Definições dos sinais
    reg clk;                     // Clock
    reg reset;                   // Sinal de reset
    reg [15:0] inM;              // Valor de entrada M (memória)
    reg [15:0] instruction;      // Instrução para execução
    wire [15:0] outM;            // Valor de saída M (memória)
    wire loadM;                  // Sinal para escrever em M
    wire [15:0] addressM;        // Endereço da memória de dados (M)
    wire [15:0] pc;              // Contador de programa (program counter)

    // Instância da CPU
    CPU uut (
        .clk(clk),
        .inM(inM),
        .instruction(instruction),
        .reset(reset),
        .outM(outM),
        .loadM(loadM),
        .addressM(addressM),
        .pc(pc)
    );

    // Gerador de clock
    always
        #1 clk = ~clk;  

    // Como os sinais irão variar durante a simulação
    initial begin
        $display("Testando o módulo CPU");
        $dumpfile("signals.vcd");
        $dumpvars(0, tb_CPU);
        // Inicializando os sinais
        clk = 0;
        reset = 0;
        inM = 16'd0;
        instruction = 16'd0;

        // Resetando a CPU
        reset = 1;
        #2;
        reset = 0;

        // Teste 1: Carregar @12345 no registrador A (A = 12345)
        instruction = 16'b0011000000111001;  // @12345
        #2;  // Espera 2 unidades de tempo (um ciclo de clock completo)
        
        // Teste 2: Executar D=A (D = 12345)
        instruction = 16'b1110110000010000;  // D=A
        #2;

        // Teste 3: Carregar @23456 no registrador A (A = 23456)
        instruction = 16'b0101101110100000;  // @23456
        #2;

        // Teste 4: Executar D=A-D (D = A-D)
        instruction = 16'b1110000111010000;  // D=A-D
        #2;

        // Teste 5: Carregar @1000 no registrador A (A = 1000)
        instruction = 16'b0000001111101000;  // @1000
        #2;

        // Teste 6: Executar M=D (M = D)
        instruction = 16'b1110001100001000;  // M=D
        #2;

        // Teste 7: Carregar @1001 no registrador A (A = 1001)
        instruction = 16'b0000001111101001;  // @1001
        #2;

        // Teste 8: Executar MD=D-1 (M e D = D-1)
        instruction = 16'b1110001110011000;  // MD=D-1
        #2;

        // Teste 9: Carregar @1000 no registrador A (A = 1000)
        instruction = 16'b0000001111101000;  // @1000
        #2;

        // Teste 10: Executar D=D-M (D = D - M)
        instruction = 16'b1111010011010000;  // D=D-M
        inM = 16'b11111;                     // Define inM como 11111 (valor da memória)
        #2;

        // Continue com os outros testes conforme necessário, usando o mesmo padrão de delays e configurações.
        
        // Finalizando a simulação
        $finish;
    end

endmodule

trab5/cpu/signals.vcd
$date
	Sat Sep 28 12:25:34 2024
$end
$version
	Icarus Verilog
$end
$timescale
	1s
$end
$scope module tb_CPU $end
$var wire 16 ! pc [15:0] $end
$var wire 16 " outM [15:0] $end
$var wire 1 # loadM $end
$var wire 16 $ addressM [15:0] $end
$var reg 1 % clk $end
$var reg 16 & inM [15:0] $end
$var reg 16 ' instruction [15:0] $end
$var reg 1 ( reset $end
$scope module uut $end
$var wire 16 ) addressM [15:0] $end
$var wire 1 % clk $end
$var wire 16 * inM [15:0] $end
$var wire 16 + instruction [15:0] $end
$var wire 1 , jmp $end
$var wire 1 - loadA $end
$var wire 1 . loadD $end
$var wire 1 / loadI $end
$var wire 1 # loadM $end
$var wire 16 0 outM [15:0] $end
$var wire 1 ( reset $end
$var wire 16 1 outALU [15:0] $end
$var wire 1 2 lt $end
$var wire 1 3 eq $end
$var wire 16 4 am [15:0] $end
$var reg 16 5 pc [15:0] $end
$var reg 16 6 regA [15:0] $end
$var reg 16 7 regD [15:0] $end
$scope module alu_0 $end
$var wire 1 8 f $end
$var wire 1 9 no $end
$var wire 1 : nx $end
$var wire 1 ; ny $end
$var wire 16 < x [15:0] $end
$var wire 16 = y [15:0] $end
$var wire 1 > zx $end
$var wire 1 ? zy $end
$var wire 1 3 zr $end
$var wire 6 @ sel [5:0] $end
$var wire 1 2 ng $end
$var reg 16 A out [15:0] $end
$upscope $end
$upscope $end
$upscope $end
$enddefinitions $end
$comment Show the parameter values. $end
$dumpall
$end
#0
$dumpvars
bx A
b0 @
0?
0>
bx =
bx <
0;
0:
09
08
bx 7
bx 6
bx 5
bx 4
x3
x2
bx 1
bx 0
1/
0.
0-
0,
b0 +
b0 *
bx )
1(
b0 '
b0 &
0%
bx $
0#
bx "
bx !
$end
#1
13
02
b0 4
b0 =
b0 "
b0 0
b0 1
b0 A
b0 !
b0 5
b0 $
b0 )
b0 6
b0 7
b0 <
1%
#2
0%
b11000000111001 '
b11000000111001 +
0(
#3
b11000000111001 $
b11000000111001 )
b11000000111001 6
b1 !
b1 5
1%
#4
03
b11000000111001 "
b11000000111001 0
b11000000111001 1
b11000000111001 A
b11000000111001 4
b11000000111001 =
0/
1.
1>
b110000 @
1:
0%
b1110110000010000 '
b1110110000010000 +
#5
b10 !
b10 5
b11000000111001 7
b11000000111001 <
1%
#6
b0 4
b0 =
1/
0.
0:
1?
1;
b101110 @
18
0%
b101101110100000 '
b101101110100000 +
#7
b101101110100000 $
b101101110100000 )
b101101110100000 6
b11 !
b11 5
1%
#8
02
b101101110100000 4
b101101110100000 =
b10101101100111 "
b10101101100111 0
b10101101100111 1
b10101101100111 A
0/
1.
0>
0?
b111 @
19
0%
b1110000111010000 '
b1110000111010000 +
#9
b11000000111001 "
b11000000111001 0
b11000000111001 1
b11000000111001 A
b100 !
b100 5
b10101101100111 7
b10101101100111 <
1%
#10
12
b1101010010011001 "
b1101010010011001 0
b1101010010011001 1
b1101010010011001 A
1/
0.
b1111 @
1?
0%
b1111101000 '
b1111101000 +
#11
b1111101000 4
b1111101000 =
b1111101000 $
b1111101000 )
b1111101000 6
b101 !
b101 5
1%
#12
02
b10101101100111 "
b10101101100111 0
b10101101100111 1
b10101101100111 A
0/
1#
08
b1100 @
09
0%
b1110001100001000 '
b1110001100001000 +
#13
b110 !
b110 5
1%
#14
12
b1101010010011001 "
b1101010010011001 0
b1101010010011001 1
b1101010010011001 A
1/
0#
18
b1111 @
19
0%
b1111101001 '
b1111101001 +
#15
b1111101001 4
b1111101001 =
b1111101001 $
b1111101001 )
b1111101001 6
b111 !
b111 5
1%
#16
0/
1.
1#
b1110 @
09
0%
b1110001110011000 '
b1110001110011000 +
#17
b1000 !
b1000 5
b1101010010011001 7
b1101010010011001 <
1%
#18
02
b10101101100111 "
b10101101100111 0
b10101101100111 1
b10101101100111 A
1/
0.
0#
b1111 @
19
0%
b1111101000 '
b1111101000 +
#19
b1111101000 4
b1111101000 =
b1111101000 $
b1111101000 )
b1111101000 6
b1001 !
b1001 5
1%
#20
12
b11111 4
b11111 =
b1101010001111010 "
b1101010001111010 0
b1101010001111010 1
b1101010001111010 A
0/
1.
1:
0?
b10011 @
0;
0%
b11111 &
b11111 *
b1111010011010000 '
b1111010011010000 +
#21
b1101010001011011 "
b1101010001011011 0
b1101010001011011 1
b1101010001011011 A
b1010 !
b1010 5
b1101010001111010 7
b1101010001111010 <
1%
