trab3/DFF_sem_rst/DFF_sem_rst.v
// Sflip flop tipo D sem rst

module DFF_sem_rst(input d, input clk, output reg q, output reg qn);
  
  always @ ( posedge clk) begin
    
      q <= d;
      qn <= ~d;
    
  end

endmodule

trab3/DFF_sem_rst/tb_DFF_sem_rst.v

// modulos usados
`include "DFF_sem_rst.v"

module tb_DFF_sem_rst;
  
  // clock simulado
  reg clk;

  // sinais
  reg d;
  wire q;
  wire qn;

  // Instancia da UUT (Unit Under Test)
  DFF_sem_rst uut (d,clk,q,qn);

   // Como os sinais irao variar durante a simulacao
  initial begin
    $display("DFF_sem_rst");
    $dumpfile("signals.vcd");
    $dumpvars(0,tb_DFF_sem_rst);
    clk = 0;
    d = 0;

    # 2 d = 0;  
    # 2 d = 1; 
    # 2 d = 1; 
    # 2 d = 0; 
    # 2 d = 1; 

    # 5 $finish;
  end

  // Monitora os sinais
  initial begin
    $monitor(clk,d,q,qn);
  end

 // gerador de clock com bloco always de unica linha
  always 
    #1 clk = ~clk;



endmodule

trab3/DFF_sem_rst/signals.vcd
$date
	Sat Aug 24 12:19:44 2024
$end
$version
	Icarus Verilog
$end
$timescale
	1s
$end
$scope module tb_DFF_sem_rst $end
$var wire 1 ! qn $end
$var wire 1 " q $end
$var reg 1 # clk $end
$var reg 1 $ d $end
$scope module uut $end
$var wire 1 # clk $end
$var wire 1 $ d $end
$var reg 1 " q $end
$var reg 1 ! qn $end
$upscope $end
$upscope $end
$enddefinitions $end
$comment Show the parameter values. $end
$dumpall
$end
#0
$dumpvars
0$
0#
x"
x!
$end
#1
1!
0"
1#
#2
0#
#3
1#
#4
0#
1$
#5
0!
1"
1#
#6
0#
#7
1#
#8
0#
0$
#9
1!
0"
1#
#10
0#
1$
#11
0!
1"
1#
