trab1/mux8way16/mux8way16.v
module mux8way16 (
    input [15:0] i0, 
    input [15:0] i1, 
    input [15:0] i2, 
    input [15:0] i3,
    input [15:0] i4, 
    input [15:0] i5, 
    input [15:0] i6,
    input [15:0] i7,
    input [2:0] sel,  
    output reg [15:0] out 
);

    always @(*) begin
        case(sel)
            3'b000: out = i0; 
            3'b001: out = i1;
            3'b010: out = i2; 
            3'b011: out = i3;
            3'b100: out = i4; 
            3'b101: out = i5;
            3'b110: out = i6; 
            3'b111: out = i7; 
            default: out = 16'b0;
        endcase
    end
endmodule

trab1/mux8way16/tb_mux8way16.v
//
// Test bench para multiplexador de 8 entradas
//
// Dicas:
// https://www.referencedesigner.com/tutorials/verilog/verilog_62.php

// modulos usados
`include "mux8way16.v"

module tb_mux8way16;
    reg [15:0] in_i0, in_i1, in_i2, in_i3, in_i4, in_i5, in_i6, in_i7;
    reg [2:0] sel;
    wire [15:0] out;
    
    // Instancia o mux4way16
    mux8way16 uut (
        .i0(in_i0),
        .i1(in_i1),
        .i2(in_i2),
        .i3(in_i3),
        .i4(in_i4),
        .i5(in_i5),
        .i6(in_i6),
        .i7(in_i7),
        .sel(sel),
        .out(out)
    );
    
    initial begin
        $display("Testbench para multiplexador de 8 entradas 16bit");
        $dumpfile("signals.vcd");
        $dumpvars(0,tb_mux8way16);
        // Inicializa as entradas
        in_i0 = 16'hAAAA;
        in_i1 = 16'hBBBB;
        in_i2 = 16'hCCCC;
        in_i3 = 16'hDDDD;
        in_i4 = 16'h0001;
        in_i5 = 16'h0010;
        in_i6 = 16'h0100;
        in_i7 = 16'h1000;

        sel = 3'b000;

        #10 sel = 3'b001;
        #10 sel = 3'b010;
        #10 sel = 3'b011;
        #10 sel = 3'b100;
        #10 sel = 3'b101;
        #10 sel = 3'b110;
        #10 sel = 3'b111;
        
        // Finaliza a simulação
        #10 $finish;
    end
    
    initial begin
        $monitor("t= %03d, sel = %b, out = %h", $time, sel, out);
    end
endmodule

trab1/mux8way16/signals.vcd
$date
	Thu Jun 06 15:06:19 2024
$end
$version
	Icarus Verilog
$end
$timescale
	1s
$end
$scope module tb_mux8way16 $end
$var wire 16 ! out [15:0] $end
$var reg 16 " in_i0 [15:0] $end
$var reg 16 # in_i1 [15:0] $end
$var reg 16 $ in_i2 [15:0] $end
$var reg 16 % in_i3 [15:0] $end
$var reg 16 & in_i4 [15:0] $end
$var reg 16 ' in_i5 [15:0] $end
$var reg 16 ( in_i6 [15:0] $end
$var reg 16 ) in_i7 [15:0] $end
$var reg 3 * sel [2:0] $end
$scope module uut $end
$var wire 16 + i0 [15:0] $end
$var wire 16 , i1 [15:0] $end
$var wire 16 - i2 [15:0] $end
$var wire 16 . i3 [15:0] $end
$var wire 16 / i4 [15:0] $end
$var wire 16 0 i5 [15:0] $end
$var wire 16 1 i6 [15:0] $end
$var wire 16 2 i7 [15:0] $end
$var wire 3 3 sel [2:0] $end
$var reg 16 4 out [15:0] $end
$upscope $end
$upscope $end
$enddefinitions $end
$comment Show the parameter values. $end
$dumpall
$end
#0
$dumpvars
b1010101010101010 4
b0 3
b1000000000000 2
b100000000 1
b10000 0
b1 /
b1101110111011101 .
b1100110011001100 -
b1011101110111011 ,
b1010101010101010 +
b0 *
b1000000000000 )
b100000000 (
b10000 '
b1 &
b1101110111011101 %
b1100110011001100 $
b1011101110111011 #
b1010101010101010 "
b1010101010101010 !
$end
#10
b1011101110111011 !
b1011101110111011 4
b1 *
b1 3
#20
b1100110011001100 !
b1100110011001100 4
b10 *
b10 3
#30
b1101110111011101 !
b1101110111011101 4
b11 *
b11 3
#40
b1 !
b1 4
b100 *
b100 3
#50
b10000 !
b10000 4
b101 *
b101 3
#60
b100000000 !
b100000000 4
b110 *
b110 3
#70
b1000000000000 !
b1000000000000 4
b111 *
b111 3
