trab3/PC/PC.v
module PC(
    input [15:0] in,      
    input        reset,   
    input        load,    
    input        inc,     
    input        clk,   
    output reg [15:0] out      
);

    always @(posedge clk or posedge reset) begin
        if (reset) begin
            out <= 16'b0;               // Reseta o contador para 0
        end else if (load) begin
            out <= in;                  // Carrega o valor da entrada 'in'
        end else if (inc) begin
            out <= out + 16'b1;         // Incrementa o contador
        end
    end

endmodule

trab3/PC/tb_PC.v
`include "PC.v"

module tb_PC;

    reg [15:0] in;      // Entrada de 16 bits
    reg reset;          // Sinal de reset
    reg load;           // Sinal de load
    reg inc;            // Sinal de incremento
    reg clk;          // Sinal de clock
    wire [15:0] out;    // Saída de 16 bits

    PC uut (
        .in(in),
        .reset(reset),
        .load(load),
        .inc(inc),
        .clk(clk),
        .out(out)
    );
    // Testes
    initial begin
        $display("Testando o módulo PC");
        $dumpfile("signals.vcd");
        $dumpvars(0, tb_PC);

        clk = 0;
        reset = 1; 
        load = 0; 
        inc = 0; 
        in = 16'b0;

        #10 reset = 0;

        
        #10 in = 16'hA5A5; load = 1;
        #10 load = 0;

        #10 inc = 1;
        #10 inc = 0;

        #10 reset = 1;
        #10 reset = 0;

        #10 in = 16'hFFFF; load = 1;
        #10 load = 0; inc = 1;
        #10 inc = 0;

        $finish;
    end

    
    always 
        #5 clk = ~clk;
endmodule

trab3/PC/signals.vcd
$date
	Sat Aug 24 17:53:43 2024
$end
$version
	Icarus Verilog
$end
$timescale
	1s
$end
$scope module tb_PC $end
$var wire 16 ! out [15:0] $end
$var reg 1 " clk $end
$var reg 16 # in [15:0] $end
$var reg 1 $ inc $end
$var reg 1 % load $end
$var reg 1 & reset $end
$scope module uut $end
$var wire 1 " clk $end
$var wire 16 ' in [15:0] $end
$var wire 1 $ inc $end
$var wire 1 % load $end
$var wire 1 & reset $end
$var reg 16 ( out [15:0] $end
$upscope $end
$upscope $end
$enddefinitions $end
$comment Show the parameter values. $end
$dumpall
$end
#0
$dumpvars
b0 (
b0 '
1&
0%
0$
b0 #
0"
b0 !
$end
#5
1"
#10
0"
0&
#15
1"
#20
0"
1%
b1010010110100101 #
b1010010110100101 '
#25
b1010010110100101 !
b1010010110100101 (
1"
#30
0"
0%
#35
1"
#40
0"
1$
#45
b1010010110100110 !
b1010010110100110 (
1"
#50
0"
0$
#55
1"
#60
b0 !
b0 (
0"
1&
#65
1"
#70
0"
0&
#75
1"
#80
0"
1%
b1111111111111111 #
b1111111111111111 '
#85
b1111111111111111 !
b1111111111111111 (
1"
#90
0"
1$
0%
#95
b0 !
b0 (
1"
#100
0"
0$
