trab3/Register/DFF_sem_rst.v
// Sflip flop tipo D sem rst

module DFF_sem_rst(input [15:0]d, input clk, output reg [15:0]q, output reg [15:0] qn);
  
  always @ ( posedge clk) begin
    
      q <= d;
      qn <= ~d;
    
  end

endmodule

trab1/mux16/mux16.v
//
// Multiplexador de duas entradas (16 bits), comportamental
//
module mux16(input [15:0] a, input [15:0] b, input sel, output [15:0] y);
  
  assign y = sel ? b : a;

endmodule

trab3/Register/Register.v
`include "DFF_sem_rst.v"
`include "mux16.v"

module Register(input [15:0] in1, input load, input clk, output reg [15:0] out);

    wire [15:0] q ;
    wire [15:0] qn ;
    wire [15:0] mux_out;

    // Instanciando o mux
    mux16 aux_mux(q, in1, load, mux_out);

    // Instanciando o flip-flop
    DFF_sem_rst dff(mux_out, clk, q, qn); 

    // Atualizando o valor de out
    always @ (posedge clk) begin
        out <= q;
    end

endmodule

trab3/Register/tb_Register.v
// módulos usados
`include "Register.v"

module tb_Register;
  
  // clock simulado
  reg clk;

  // sinais
  reg [15:0] in1;
  reg load;
  wire [15:0] out;
  
  // Instância da UUT (Unit Under Test)
  Register uut (
    in1, 
    load, 
    clk, 
    out
  );

  // Como os sinais irão variar durante a simulação
  initial begin
    $display("Testando o módulo Register");
    $dumpfile("signals.vcd");
    $dumpvars(0, tb_Register);
    
    // Inicialização dos sinais
    clk = 0;
    in1 = 0;
    load = 0;

    // Sequência de teste
    #2 in1 = 16'b0000000000000001;  load = 1;// Carrega '1' no registrador
    #2 load = 0;                             // Desativa o carregamento
    #2 in1 = 16'b0000000000000010;           // Muda o valor de in1, mas sem carregar
    #2 load = 1;                             // Carrega '2' no registrador
    #2 load = 0;
    #2 in1 = 16'hFFFF; load = 1; // Carrega '1' novamente
    #2 load = 0;

    #5 $finish;
  end

  // Monitora os sinais
  initial begin
    $monitor("Tempo = %0t | clk = %b | load = %b | in1 = %b | out = %b", $time, clk, load, in1, out);
  end

  // Gerador de clock
  always 
    #1 clk = ~clk;

endmodule

trab3/Register/signals.vcd
$date
	Sat Aug 24 16:51:30 2024
$end
$version
	Icarus Verilog
$end
$timescale
	1s
$end
$scope module tb_Register $end
$var wire 16 ! out [15:0] $end
$var reg 1 " clk $end
$var reg 16 # in1 [15:0] $end
$var reg 1 $ load $end
$scope module uut $end
$var wire 1 " clk $end
$var wire 16 % in1 [15:0] $end
$var wire 1 $ load $end
$var wire 16 & qn [15:0] $end
$var wire 16 ' q [15:0] $end
$var wire 16 ( mux_out [15:0] $end
$var reg 16 ) out [15:0] $end
$scope module aux_mux $end
$var wire 16 * b [15:0] $end
$var wire 1 $ sel $end
$var wire 16 + y [15:0] $end
$var wire 16 , a [15:0] $end
$upscope $end
$scope module dff $end
$var wire 1 " clk $end
$var wire 16 - d [15:0] $end
$var reg 16 . q [15:0] $end
$var reg 16 / qn [15:0] $end
$upscope $end
$upscope $end
$upscope $end
$enddefinitions $end
$comment Show the parameter values. $end
$dumpall
$end
#0
$dumpvars
bx /
bx .
bx -
bx ,
bx +
b0 *
bx )
bx (
bx '
bx &
b0 %
0$
b0 #
0"
bx !
$end
#1
1"
#2
b1 (
b1 +
b1 -
0"
1$
b1 #
b1 %
b1 *
#3
b1111111111111110 &
b1111111111111110 /
b1 '
b1 ,
b1 .
1"
#4
0"
0$
#5
b1 !
b1 )
1"
#6
0"
b10 #
b10 %
b10 *
#7
1"
#8
b10 (
b10 +
b10 -
0"
1$
#9
b1111111111111101 &
b1111111111111101 /
b10 '
b10 ,
b10 .
1"
#10
0"
0$
#11
b10 !
b10 )
1"
#12
b1111111111111111 (
b1111111111111111 +
b1111111111111111 -
0"
1$
b1111111111111111 #
b1111111111111111 %
b1111111111111111 *
#13
b0 &
b0 /
b1111111111111111 '
b1111111111111111 ,
b1111111111111111 .
1"
#14
0"
0$
#15
b1111111111111111 !
b1111111111111111 )
1"
