trab3/RAM8/RAM8.v
module RAM8(
    input  [15:0] in,
    input  [2:0]  address,
    input         load,
    input         clk,
    output reg [15:0] out 
);
    reg [15:0] ram [7:0]; // Define 8 registradores de 16 bits cada

    always @ (*) begin
        if (load) begin
            ram[address] <= in; 
        end

        out = ram[address]; 
    end
    
endmodule

trab3/RAM8/tb_RAM8.v
`include "RAM8.v"

module tb_RAM8;

    reg [15:0]  in;
    reg [2:0]   address;
    reg load; 
    reg clk;
    wire [15:0] out;

    RAM8 uut(in, address, load, clk, out);


    initial begin
        $display("Testando o módulo RAM8");
        $dumpfile("signals.vcd");
        $dumpvars(0, tb_RAM8);
        // load in data
        clk = 0;
        load = 1;
        in = 0;

        in = 16'b0000000000000000; address = 3'b000; // address 0
        #2 in = 16'b1111111111111111; address = 3'b001; // address 1
        #2 in = 16'b0000000011111111; address = 3'b010;load = 0; // address 2
        #2 in = 16'b1111111100000000; address = 3'b011;load = 1; // address 3
        #2 in = 16'b0000111100001111; address = 3'b100; // address 4
        #2 in = 16'b1111000011110000; address = 3'b101; // address 5
        #2 in = 16'b0011001100110011; address = 3'b110; // address 6
        #2 in = 16'b1100110011001100; address = 3'b111; // address 7
        #5 $finish;
    end
        // Monitora os sinais
    initial begin
        $monitor("Tempo = %0t | clk = %b | address = %b | out = %b", $time, clk, address, out);
    end

    always 
        #2 clk = ~clk;
        

endmodule

trab3/RAM8/signals.vcd
$date
	Sat Aug 24 17:07:11 2024
$end
$version
	Icarus Verilog
$end
$timescale
	1s
$end
$scope module tb_RAM8 $end
$var wire 16 ! out [15:0] $end
$var reg 3 " address [2:0] $end
$var reg 1 # clk $end
$var reg 16 $ in [15:0] $end
$var reg 1 % load $end
$scope module uut $end
$var wire 3 & address [2:0] $end
$var wire 1 # clk $end
$var wire 16 ' in [15:0] $end
$var wire 1 % load $end
$var reg 16 ( out [15:0] $end
$upscope $end
$upscope $end
$enddefinitions $end
$comment Show the parameter values. $end
$dumpall
$end
#0
$dumpvars
b0 (
b0 '
b0 &
1%
b0 $
0#
b0 "
b0 !
$end
#2
b1111111111111111 !
b1111111111111111 (
1#
b1 "
b1 &
b1111111111111111 $
b1111111111111111 '
#4
bx !
bx (
0#
0%
b10 "
b10 &
b11111111 $
b11111111 '
#6
b1111111100000000 !
b1111111100000000 (
1#
1%
b11 "
b11 &
b1111111100000000 $
b1111111100000000 '
#8
b111100001111 !
b111100001111 (
0#
b100 "
b100 &
b111100001111 $
b111100001111 '
#10
b1111000011110000 !
b1111000011110000 (
1#
b101 "
b101 &
b1111000011110000 $
b1111000011110000 '
#12
b11001100110011 !
b11001100110011 (
0#
b110 "
b110 &
b11001100110011 $
b11001100110011 '
#14
b1100110011001100 !
b1100110011001100 (
1#
b111 "
b111 &
b1100110011001100 $
b1100110011001100 '
