trab2/fulladder/halfadder.v
//
// Meio somador de 1 bit (comportamental)
//
module halfadder(input a, input b, output sum, output carry_out);
  
  assign sum = a ^ b;
  assign carry_out = a & b;

endmodule

trab2/fulladder/fulladder.v
//
// Somador completo de 1 bit reusando o meio somador combinacional
//
`include "halfadder.v"

module fulladder(input a, input b, input carry_in, output sum, output carry_out);
  
  wire s1, c1, c2;
  
  halfadder h1(a, b, s1, c1);
  halfadder h2(s1, carry_in, sum, c2);

  assign carry_out = c1 | c2;

endmodule

trab2/fulladder/tb_fulladder.v

`include "fulladder.v"

module tb_fadders;
  
  // inputs
  reg in_a;
  reg in_b;
  reg in_c;
  // outputs
  wire out_s;
  wire out_c;

  

  // Instancia da UUT (Unit Under Test)
  fulladder uut (.a(in_a), .b(in_b), .carry_in(in_c), .sum(out_s), .carry_out(out_c));

  // Como os sinais irao variar durante a simulacao
  initial begin
    $display("Testbench para full adder estrutural");
    $dumpfile("signals.vcd");
    $dumpvars(0);

    # 0 in_a = 0; in_b = 0; in_c = 0;
    # 10 in_a = 0; in_b = 0; in_c = 1;
    # 10 in_a = 0; in_b = 1; in_c = 0;
    # 10 in_a = 0; in_b = 1; in_c = 1;
    # 10 in_a = 1; in_b = 0; in_c = 0;
    # 10 in_a = 1; in_b = 0; in_c = 1;
    # 10 in_a = 1; in_b = 1; in_c = 0;
    # 10 in_a = 1; in_b = 1; in_c = 1;
    
    # 10 $finish;
  end

  // Monitora os sinais
  initial begin
    $monitor("t=%03d: \ta=%d,b=%d,s=%d,c=%d",$time,in_a,in_b,out_s,out_c);
  end

endmodule

trab2/fulladder/signals.vcd
$date
	Thu Jun 06 17:27:59 2024
$end
$version
	Icarus Verilog
$end
$timescale
	1s
$end
$scope module tb_fadders $end
$var wire 1 ! out_s $end
$var wire 1 " out_c $end
$var reg 1 # in_a $end
$var reg 1 $ in_b $end
$var reg 1 % in_c $end
$scope module uut $end
$var wire 1 # a $end
$var wire 1 $ b $end
$var wire 1 % carry_in $end
$var wire 1 " carry_out $end
$var wire 1 ! sum $end
$var wire 1 & s1 $end
$var wire 1 ' c2 $end
$var wire 1 ( c1 $end
$scope module h1 $end
$var wire 1 # a $end
$var wire 1 $ b $end
$var wire 1 ( carry_out $end
$var wire 1 & sum $end
$upscope $end
$scope module h2 $end
$var wire 1 & a $end
$var wire 1 % b $end
$var wire 1 ' carry_out $end
$var wire 1 ! sum $end
$upscope $end
$upscope $end
$upscope $end
$enddefinitions $end
$comment Show the parameter values. $end
$dumpall
$end
#0
$dumpvars
0(
0'
0&
0%
0$
0#
0"
0!
$end
#10
1!
1%
#20
1&
0%
1$
#30
1"
0!
1'
1%
#40
0"
1!
0'
0%
0$
1#
#50
1"
0!
1'
1%
#60
0'
0&
1(
0%
1$
#70
1!
1%
